methodism/__init__.py
methodism/costumizing.py
methodism/decors.py
methodism/error_messages.py
methodism/helper.py
methodism/main.py
methodism/models.py
methodism/paginator.py
methodism/sqlpaginator.py
methodism-0.3.4.dist-info/METADATA
methodism-0.3.4.dist-info/WHEEL
methodism-0.3.4.dist-info/top_level.txt
methodism-0.3.4.dist-info/RECORD
