Metadata-Version: 2.4
Name: methodism
Version: 0.3.4
Summary: Help to build APIs Faster
Home-page: https://github.com/xudoyberdi123/Methodism
Author: xudikk
Author-email: xudikk <xudikk.1@gmail.com>
Project-URL: Homepage, https://github.com/xudikk/Methodism
Classifier: Programming Language :: Python :: 3
Classifier: License :: OSI Approved :: MIT License
Classifier: Operating System :: OS Independent
Requires-Python: >=3.8
Requires-Dist: Django>=5.2
Requires-Dist: djangorestframework>=3.16.0
